{
  "category": "INSTRUMENTO",
  "pattern_count": 2,
  "patterns": {
    "PAT-0163": {
      "id": "PAT-0163",
      "canonical_id": "PAT-0163",
      "legacy_ids": [
        "PAT-0163",
        "PAT-Q007-001"
      ],
      "pattern_spec": {
        "type": "REGEX",
        "pattern": "talleres de|capacitaciones en|jornadas de|mesas de trabajo|formación en",
        "flags": [
          "IGNORECASE",
          "MULTILINE"
        ],
        "captures": {}
      },
      "classification": {
        "category": "INSTRUMENTO",
        "subcategory": "",
        "specificity": "MEDIUM",
        "confidence_weight": 0.85
      },
      "bindings": {
        "applies_to_dimensions": [
          "DIM02"
        ],
        "applies_to_questions": [
          "Q007"
        ],
        "applies_to_policy_areas": [
          "PA01"
        ],
        "applies_to_membership_criteria": []
      },
      "scoring_impact": {
        "weight_in_scoring": 0.15,
        "boost_conditions": [],
        "penalty_conditions": []
      },
      "provenance": {
        "source_file": "pattern_registry.json",
        "created_at": "2026-01-06T19:55:24.978173+00:00",
        "validated": false,
        "validation_tests": []
      },
      "examples": {
        "positive": [],
        "negative": []
      }
    },
    "PAT-0164": {
      "id": "PAT-0164",
      "canonical_id": "PAT-0164",
      "legacy_ids": [
        "PAT-0164",
        "PAT-Q007-002"
      ],
      "pattern_spec": {
        "type": "REGEX",
        "pattern": "capital semilla|incentivos económicos|apoyo a emprendimientos|subsidios|transferencias",
        "flags": [
          "IGNORECASE",
          "MULTILINE"
        ],
        "captures": {}
      },
      "classification": {
        "category": "INSTRUMENTO",
        "subcategory": "",
        "specificity": "MEDIUM",
        "confidence_weight": 0.85
      },
      "bindings": {
        "applies_to_dimensions": [
          "DIM02"
        ],
        "applies_to_questions": [
          "Q007"
        ],
        "applies_to_policy_areas": [
          "PA01"
        ],
        "applies_to_membership_criteria": []
      },
      "scoring_impact": {
        "weight_in_scoring": 0.15,
        "boost_conditions": [],
        "penalty_conditions": []
      },
      "provenance": {
        "source_file": "pattern_registry.json",
        "created_at": "2026-01-06T19:55:24.978184+00:00",
        "validated": false,
        "validation_tests": []
      },
      "examples": {
        "positive": [],
        "negative": []
      }
    }
  }
}