{
  "$schema": "../aggregation_schema.json",
  "_schema_version": "2.0.0",
  
  "cluster_id": "CL02",
  "cluster_name": "Grupos Poblacionales",
  "cluster_description": "Agrupa políticas de atención a poblaciones específicas",
  
  "composition": {
    "policy_areas": ["PA01", "PA05", "PA06"],
    "policy_area_names": {
      "PA01": "Mujeres y Género",
      "PA05": "Víctimas y Paz",
      "PA06": "Niñez, Adolescencia y Juventud"
    }
  },
  
  "aggregation": {
    "method": "WEIGHTED_AVERAGE_WITH_COHERENCE_BONUS",
    
    "policy_area_weights": {
      "PA01": 0.30,
      "PA05": 0.40,
      "PA06": 0.30
    },
    
    "weight_rationale": {
      "PA01": "Peso medio por transversalidad de género",
      "PA05": "Mayor peso por obligatoriedad en municipios PDET - Decreto 893/2017 y concentración de víctimas del conflicto armado",
      "PA06": "Peso medio por prioridad de protección",
      "pdet_note": "En contextos PDET, PA05 tiene peso elevado debido a mandato legal de incorporación de PATR y alta concentración de población victimizada"
    },
    
    "coherence_bonus": {
      "enabled": true,
      "max_bonus": 0.15,
      
      "criteria": {
        "enfoque_diferencial": {
          "description": "Presencia de enfoque diferencial explícito",
          "detection": {
            "cc_theme": "CC_ENFOQUE_DIFERENCIAL",
            "min_score": 0.60
          },
          "weight": 0.50
        },
        
        "intersectional_approach": {
          "description": "Análisis interseccional (género + víctimas + niñez)",
          "detection": {
            "type": "CO_OCCURRENCE_ACROSS_PA",
            "terms": ["mujeres víctimas", "niños víctimas", "enfoque de género"]
          },
          "weight": 0.30
        },
        
        "normative_alignment": {
          "required_norms": ["Ley 1257 de 2008", "Ley 1448 de 2011", "Ley 1098 de 2006"],
          "weight": 0.20,
          "pdet_specific_norms": [
            "Decreto Ley 893 de 2017 (PDET)",
            "Acuerdo de Paz - Punto 1 (Reforma Rural Integral)",
            "Acuerdo de Paz - Punto 5 (Víctimas)",
            "Plan Marco de Implementación (PMI)"
          ],
          "pdet_note": "Para municipios PDET, se valora positivamente la mención explícita de PATR, Plan Marco de Implementación y Decreto 893/2017"
        }
      }
    },
    
    "final_formula": "MESO_SCORE = (PA01_score * 0.30 + PA05_score * 0.40 + PA06_score * 0.30) + coherence_bonus"
  },
  
  "meso_question": {
    "question_id": "MESO-CL02",
    "text": {
      "es": "¿El plan integra coherentemente la atención a mujeres, víctimas, y niñez/juventud con enfoque diferencial?",
      "en": "Does the plan coherently integrate attention to women, victims, and children/youth with a differential approach?"
    }
  },
  
  "thresholds": {
    "EXCELENTE": {"min": 0.85, "color": "#22c55e"},
    "BUENO": {"min": 0.70, "color": "#3b82f6"},
    "ACEPTABLE": {"min": 0.55, "color": "#eab308"},
    "INSUFICIENTE": {"min": 0.0, "color": "#ef4444"}
  },
  
  "signal_preservation": {
    "preserve_top_signals": 5,
    "preserve_types": ["NORMATIVE_REFERENCE", "POPULATION_DISAGGREGATION", "QUANTITATIVE_TRIPLET"]
  },
  
  "pdet_enrichment": {
    "contextual_scope": "Municipalities within 170 PDET territories across 16 subregions",
    "territorial_markers": {
      "veredas": "PDET covers approximately 11,000 veredas - territorial disaggregation to vereda level is highly valued",
      "subregions": [
        "Alto Patía y Norte del Cauca",
        "Arauca",
        "Bajo Cauca y Nordeste Antioqueño",
        "Catatumbo",
        "Chocó",
        "Cuenca del Caguán",
        "Macarena-Guaviare",
        "Montes de María",
        "Pacífico Medio",
        "Pacífico y Frontera Nariñense",
        "Putumayo",
        "Sierra Nevada-Perijá",
        "Sur de Bolívar",
        "Sur de Córdoba",
        "Sur del Tolima",
        "Urabá Antioqueño"
      ],
      "ethnic_territories": "Resguardos indígenas, consejos comunitarios afrocolombianos, zonas de reserva campesina"
    },
    "consumer_integrity_requirements": {
      "scope": "Plans must explicitly address population groups in PDET contexts with territorial specificity",
      "value": "Enrichment provides mechanisms to detect PATR integration, ethnic consultation, and rural disaggregation",
      "capability": "Patterns enable identification of institutional actors (ART, Unidad de Víctimas) and financing sources (SGR-Paz, Obras por Impuestos)",
      "integrity": "Cross-validation with PATR initiatives (32,808 total) and 8 PDET pillars ensures coherence"
    },
    "key_indicators_pdet": {
      "multidimensional_poverty": "39.2% in PDET vs national average",
      "ethnic_initiative_lag": "25.15% of ethnic PDET initiatives have active implementation route",
      "total_patr_initiatives": 32808,
      "active_route_initiatives": 20352,
      "completed_works": 5759,
      "population_coverage": "6.6 million people (24% of Colombia's rural population)"
    },
    "validation_enhancement": {
      "territorial_coherence": "Verify mention of specific PDET subregion and veredas/corregimientos",
      "institutional_articulation": "Detect references to ART, OCAD Paz, Unidad de Víctimas, ethnic consultation bodies",
      "financing_traceability": "Identify SGR-Asignación para la Paz, Obras por Impuestos, or PATR initiative codes",
      "pillar_alignment": "Map interventions to PDET's 8 pillars, especially Pillar 8 (Reconciliation) for groups poblacionales"
    }
  }
}
